guano.py
guano-1.0.16.data/scripts/batlogger2guano.py
guano-1.0.16.data/scripts/d500x2guano.py
guano-1.0.16.data/scripts/disperse.py
guano-1.0.16.data/scripts/guano_dump.py
guano-1.0.16.data/scripts/guano_edit.py
guano-1.0.16.data/scripts/sb2guano.py
guano-1.0.16.data/scripts/wamd2guano.py
guano-1.0.16.dist-info/LICENSE.txt
guano-1.0.16.dist-info/METADATA
guano-1.0.16.dist-info/WHEEL
guano-1.0.16.dist-info/top_level.txt
guano-1.0.16.dist-info/RECORD
