Metadata-Version: 2.1
Name: guano
Version: 1.0.16
Summary: GUANO, the "Grand Unified" bat acoustics metadata format
Home-page: https://github.com/riggsd/guano-py
Author: David A. Riggs
Author-email: driggs@myotisoft.com
License: MIT
Keywords: bats acoustics metadata guano
Platform: UNKNOWN
Classifier: Development Status :: 5 - Production/Stable
Classifier: Intended Audience :: Developers
Classifier: Intended Audience :: Science/Research
Classifier: License :: OSI Approved :: MIT License
Classifier: Programming Language :: Python :: 3
